clipboard_monitor/__init__.py
clipboard_monitor/__main__.py
clipboard_monitor-1.0.5.dist-info/LICENSE
clipboard_monitor-1.0.5.dist-info/METADATA
clipboard_monitor-1.0.5.dist-info/WHEEL
clipboard_monitor-1.0.5.dist-info/top_level.txt
clipboard_monitor-1.0.5.dist-info/RECORD
