Metadata-Version: 2.1
Name: clipboard-monitor
Version: 1.0.5
Summary: Monitor Clipboard changes and trigger related actions
Home-page: https://github.com/cylin2000/clipboard_monitor/
Author: Calvin Cai
Author-email: cylin2000@163.com
License: MIT
Platform: UNKNOWN
Classifier: License :: OSI Approved :: MIT License
Classifier: Programming Language :: Python :: 3
Classifier: Programming Language :: Python :: 3.7
License-File: LICENSE
